example.py
python_table_print/__init__.py
python_table_print/cell.py
python_table_print/column.py
python_table_print/justification.py
python_table_print/row.py
python_table_print/table.py
python_table_print/table_exception.py
python_table_print-1.0.0.dist-info/LICENSE
python_table_print-1.0.0.dist-info/METADATA
python_table_print-1.0.0.dist-info/WHEEL
python_table_print-1.0.0.dist-info/top_level.txt
python_table_print-1.0.0.dist-info/RECORD
