Metadata-Version: 2.1
Name: python-table-print
Version: 1.0.0
Summary: Allows for pretty printing and automatic resizing of tables.
Author: Centauri_Prime
Classifier: Programming Language :: Python :: 3
Classifier: License :: OSI Approved :: MIT License
Classifier: Operating System :: OS Independent
Requires-Python: >=3
License-File: LICENSE
